qr2scad
