Metadata-Version: 1.1
Name: qr2scad
Version: 0.7.1
Summary: QR code to OpenSCAD converter
Home-page: https://github.com/l0b0/qr2scad
Author: Victor Engmark
Author-email: victor.engmark@gmail.com
License: GPL v3 or newer
Download-URL: https://github.com/l0b0/qr2scad/tarball/v0.7.1
Keywords: QR code QRcode convert converter OpenSCAD SCAD CAD
Platform: POSIX
Platform: Windows
Classifier: Development Status :: 3 - Alpha
Classifier: Environment :: Console
Classifier: Intended Audience :: End Users/Desktop
Classifier: License :: OSI Approved :: GNU General Public License (GPL)
Classifier: Operating System :: OS Independent
Classifier: Programming Language :: Python :: 2.7
Classifier: Topic :: Artistic Software
Classifier: Topic :: Multimedia :: Graphics :: 3D Modeling
Classifier: Topic :: Multimedia :: Graphics :: Graphics Conversion
